{
  "version": "40.0.0",
  "files": {
    "e10d9d7cc0237c3bd367b5c5a1c2be134c7fb75206c7cd100ebfcb710dc46333": {
      "source": {
        "path": "Ecr.template.json",
        "packaging": "file"
      },
      "destinations": {
        "current_account-current_region": {
          "bucketName": "cdk-hnb659fds-assets-${AWS::AccountId}-${AWS::Region}",
          "objectKey": "e10d9d7cc0237c3bd367b5c5a1c2be134c7fb75206c7cd100ebfcb710dc46333.json",
          "assumeRoleArn": "arn:${AWS::Partition}:iam::${AWS::AccountId}:role/cdk-hnb659fds-file-publishing-role-${AWS::AccountId}-${AWS::Region}"
        }
      }
    }
  },
  "dockerImages": {}
}